[
  {
    "id": 1,
    "title": "Spritz",
    "photos": [],
    "black": false,
    "sizeWidth": 0,
    "sizeHeight": 0,
    "collection": "cocktail",
    "date": "2022-08-15",
    "reference": "",
    "thumbnail": {
      "id": 1,
      "url": "assets/img/projects/cocktail/spritz.jpg",
      "title": "",
      "description": ""
    }
  },
  {
    "id": 2,
    "title": "Pina Colada",
    "photos": [],
    "black": false,
    "sizeWidth": 0,
    "sizeHeight": 0,
    "collection": "cocktail",
    "date": "2022-08-15",
    "reference": "",
    "thumbnail": {
      "id": 1,
      "url": "assets/img/projects/cocktail/pina.jpg",
      "title": "",
      "description": ""
    }
  },
  {
    "id": 3,
    "title": "Mojito",
    "photos": [],
    "black": false,
    "sizeWidth": 0,
    "sizeHeight": 0,
    "collection": "cocktail",
    "date": "2022-08-15",
    "reference": "",
    "thumbnail": {
      "id": 1,
      "url": "assets/img/projects/cocktail/mojito.jpg",
      "title": "",
      "description": ""
    }
  }
]
